chosung/__init__.py
chosungify-0.0.1.dist-info/LICENSE.txt
chosungify-0.0.1.dist-info/METADATA
chosungify-0.0.1.dist-info/WHEEL
chosungify-0.0.1.dist-info/top_level.txt
chosungify-0.0.1.dist-info/RECORD
