Metadata-Version: 2.1
Name: chosungify
Version: 0.0.1
Summary: Small snippet for extracting korean consonant character.
Home-page: https://github.com/SHUcream00/chosungify
Author: Joon-Won Choi
Author-email: requiemdeciel@gmail.com
License: UNKNOWN
Platform: UNKNOWN
Classifier: Programming Language :: Python :: 3
Classifier: License :: OSI Approved :: MIT License
Classifier: Operating System :: OS Independent
Requires-Python: >=3.5
